pytire/__init__.py
pytire/constant.py
pytire/enums.py
pytire/geometry.py
pytire/tire.py
pytire-0.4.1.dist-info/LICENSE
pytire-0.4.1.dist-info/WHEEL
pytire-0.4.1.dist-info/METADATA
pytire-0.4.1.dist-info/RECORD
