Metadata-Version: 2.1
Name: pytire
Version: 0.4.1
Summary: Python library to handle tire attributes.
Home-page: https://github.com/girotobial/pytire
License: MIT
Author: girotobial
Author-email: abrobinson1907@gmail.com
Requires-Python: >=3.7,<3.11
Classifier: Intended Audience :: Manufacturing
Classifier: License :: OSI Approved :: MIT License
Classifier: Programming Language :: Python :: 3
Classifier: Programming Language :: Python :: 3.10
Classifier: Programming Language :: Python :: 3.7
Classifier: Programming Language :: Python :: 3.8
Classifier: Programming Language :: Python :: 3.9
Classifier: Topic :: Software Development :: Libraries :: Python Modules
Project-URL: Documentation, https://pytire.readthedocs.io/en/latest/index.html
Project-URL: Repository, https://github.com/girotobial/pytire
